README.md
setup.py
MimePost/__init__.py
MimePost/api_client.py
MimePost/configuration.py
MimePost/rest.py
MimePost.egg-info/PKG-INFO
MimePost.egg-info/SOURCES.txt
MimePost.egg-info/dependency_links.txt
MimePost.egg-info/requires.txt
MimePost.egg-info/top_level.txt
MimePost/api/__init__.py
MimePost/api/accounts_api.py
MimePost/api/domains_api.py
MimePost/api/emails_api.py
MimePost/api/stats_api.py
MimePost/api/webhooks_api.py
MimePost/models/__init__.py
MimePost/models/account_profile.py
MimePost/models/account_profile_response.py
MimePost/models/account_settings.py
MimePost/models/api_response.py
MimePost/models/api_response_all_webhooks.py
MimePost/models/api_response_all_webhooks_data.py
MimePost/models/api_response_domains_list.py
MimePost/models/api_response_domains_list_data.py
MimePost/models/api_response_emaillogs.py
MimePost/models/api_response_emaillogs_data.py
MimePost/models/api_response_single_webhooks.py
MimePost/models/api_response_stats.py
MimePost/models/api_response_stats_data.py
MimePost/models/api_response_stats_data_datewise_summary.py
MimePost/models/api_response_stats_data_graph_summary.py
MimePost/models/api_response_stats_data_total_summary.py
MimePost/models/api_response_stats_data_total_summary_status.py
MimePost/models/api_response_webhooks.py
MimePost/models/api_response_webhooks_data.py
MimePost/models/domain.py
MimePost/models/email.py
MimePost/models/email_attachments.py
MimePost/models/email_global_merge_vars.py
MimePost/models/email_merge_vars.py
MimePost/models/email_to.py
MimePost/models/webhook.py
MimePost/models/webhook1.py
test/__init__.py
test/test_account_profile.py
test/test_account_profile_response.py
test/test_account_settings.py
test/test_accounts_api.py
test/test_api_response.py
test/test_api_response_all_webhooks.py
test/test_api_response_all_webhooks_data.py
test/test_api_response_domains_list.py
test/test_api_response_domains_list_data.py
test/test_api_response_emaillogs.py
test/test_api_response_emaillogs_data.py
test/test_api_response_single_webhooks.py
test/test_api_response_stats.py
test/test_api_response_stats_data.py
