Metadata-Version: 1.0
Name: MimePost
Version: 1.0.0
Summary: MimePost API Reference (Beta)
Home-page: UNKNOWN
Author: UNKNOWN
Author-email: support@mimepost.com
License: UNKNOWN
Keywords: Swagger,MimePost API Reference (Beta)
Platform: UNKNOWN
